wtforms_recaptcha-0.3.2.dist-info/metadata.json
wtforms_recaptcha-0.3.2.dist-info/top_level.txt
wtforms_recaptcha-0.3.2.dist-info/RECORD
wtforms_recaptcha-0.3.2.dist-info/DESCRIPTION.rst
wtforms_recaptcha-0.3.2.dist-info/WHEEL
wtforms_recaptcha-0.3.2.dist-info/METADATA
wtfrecaptcha/fields.py
wtfrecaptcha/widgets.py
wtfrecaptcha/validators.py
wtfrecaptcha/__init__.py
