Metadata-Version: 1.1
Name: wtforms-recaptcha
Version: 0.3.2
Summary: Custom WTForms field that handles reCaptcha display and validation
Home-page: http://bitbucket.org/excieve/wtforms-recaptcha
Author: Artem Gluvchynsky
Author-email: excieve@gmail.com
License: BSD
Platform: any
Classifier: Development Status :: 4 - Beta
Classifier: Environment :: Web Environment
Classifier: Intended Audience :: Developers
Classifier: License :: OSI Approved :: BSD License
Classifier: Operating System :: OS Independent
Classifier: Programming Language :: Python
Classifier: Programming Language :: Python :: 2
Classifier: Programming Language :: Python :: 3
Classifier: Topic :: Internet :: WWW/HTTP :: Dynamic Content
Classifier: Topic :: Software Development :: Libraries :: Python Modules
